docker_stuff/kube_config_inline
docker_stuff/airflow/Dockerfile
docker_stuff/docker-compose/docker-compose-minikube-network.yml
docker_stuff/docker-compose/docker-compose.yml
docker_stuff/docker-compose/entrypoint.sh
docker_stuff/mlflow/Dockerfile
docker_stuff/mlflow/requirements.txt
docker_stuff/user-package/Dockerfile
gaiaflow/__init__.py
gaiaflow/constants.py
gaiaflow/cli/__init__.py
gaiaflow/cli/cli.py
gaiaflow/cli/commands/__init__.py
gaiaflow/cli/commands/minikube.py
gaiaflow/cli/commands/mlflow_model.py
gaiaflow/cli/commands/mlops.py
gaiaflow/core/__init__.py
gaiaflow/core/create_task.py
gaiaflow/core/operators.py
gaiaflow/core/runner.py
gaiaflow/core/utils.py
gaiaflow/managers/__init__.py
gaiaflow/managers/base_manager.py
gaiaflow/managers/minikube_manager.py
gaiaflow/managers/mlflow_model_manager.py
gaiaflow/managers/mlops_manager.py
gaiaflow/managers/utils.py
gaiaflow-0.0.3.dist-info/METADATA
gaiaflow-0.0.3.dist-info/WHEEL
gaiaflow-0.0.3.dist-info/entry_points.txt
gaiaflow-0.0.3.dist-info/licenses/LICENSE
gaiaflow-0.0.3.dist-info/RECORD
